entityfaker/__init__.py
entityfaker/datasets.py
entityfaker/entities..py
entityfaker/entitykeywordgenerator.py
entityfaker/formatgenerator.py
entityfaker/formatprovider.py
entityfaker/insertlocations.py
entityfaker/keywords.py
enity_faker-0.0.10.dist-info/LICENSE
enity_faker-0.0.10.dist-info/METADATA
enity_faker-0.0.10.dist-info/WHEEL
enity_faker-0.0.10.dist-info/top_level.txt
enity_faker-0.0.10.dist-info/RECORD
