Metadata-Version: 2.1
Name: enity-faker
Version: 0.0.10
Summary: Generates fakes for different entities
Home-page: https://o365exchange.visualstudio.com/O365%20Sandbox/_git/IPMLExp?path=%2Fsrc%2FPanini2%2FSyntheticDataGenerator&version=GBmaster
Author: Anil Vemula
Author-email: v-anvemu@microsoft.com
License: UNKNOWN
Platform: UNKNOWN
Classifier: Programming Language :: Python :: 3
Classifier: License :: OSI Approved :: MIT License
Classifier: Operating System :: OS Independent
Requires-Python: >=3.6
Requires-Dist: spacy
Requires-Dist: faker
